odoo/addons/web_archive_date/README.rst
odoo/addons/web_archive_date/__init__.py
odoo/addons/web_archive_date/__manifest__.py
odoo/addons/web_archive_date/i18n/web_archive_date.pot
odoo/addons/web_archive_date/models/__init__.py
odoo/addons/web_archive_date/models/base.py
odoo/addons/web_archive_date/readme/CONTRIBUTORS.rst
odoo/addons/web_archive_date/readme/DESCRIPTION.rst
odoo/addons/web_archive_date/readme/ROADMAP.rst
odoo/addons/web_archive_date/readme/USAGE.rst
odoo/addons/web_archive_date/static/description/icon.png
odoo/addons/web_archive_date/static/description/index.html
odoo/addons/web_archive_date/static/src/js/debug_manager.esm.js
odoo/addons/web_archive_date/static/src/xml/debug.xml
odoo/addons/web_archive_date/tests/__init__.py
odoo/addons/web_archive_date/tests/test_web_archive_date.py
odoo_addon_web_archive_date-15.0.1.0.0.3.dist-info/METADATA
odoo_addon_web_archive_date-15.0.1.0.0.3.dist-info/WHEEL
odoo_addon_web_archive_date-15.0.1.0.0.3.dist-info/top_level.txt
odoo_addon_web_archive_date-15.0.1.0.0.3.dist-info/RECORD
